nbiot/__init__.py
nbiot/nbiot.py
nbiot/nbiot_test.py
telenor_nbiot-0.3.dist-info/DESCRIPTION.rst
telenor_nbiot-0.3.dist-info/METADATA
telenor_nbiot-0.3.dist-info/RECORD
telenor_nbiot-0.3.dist-info/WHEEL
telenor_nbiot-0.3.dist-info/metadata.json
telenor_nbiot-0.3.dist-info/top_level.txt
