Metadata-Version: 2.0
Name: telenor-nbiot
Version: 0.3
Summary: Telenor NB-IoT client
Home-page: https://nbiot.engineering/
Author: Exploratory Engineering
Author-email: ee@telenordigital.com
License: UNKNOWN
Project-URL: Source, https://github.com/telenordigital/nbiot-python/
Keywords: nbiot iot
Platform: UNKNOWN
Classifier: Development Status :: 3 - Alpha
Classifier: Intended Audience :: Developers
Classifier: License :: OSI Approved :: Apache Software License
Classifier: Programming Language :: Python :: 3
Classifier: Programming Language :: Python :: 3.7
Requires-Python: >=3.7
Requires-Dist: requests (>=2.20.0)
Requires-Dist: websockets
